vila/__init__.py
vila/automodel.py
vila/constants.py
vila/predictors.py
vila/utils.py
vila/dataset/__init__.py
vila/dataset/preprocessors/__init__.py
vila/dataset/preprocessors/base.py
vila/dataset/preprocessors/config.py
vila/dataset/preprocessors/grouping.py
vila/dataset/preprocessors/hierarchical_modeling.py
vila/dataset/preprocessors/layout_indicator.py
vila/models/__init__.py
vila/models/configuration_hierarchical_model.py
vila/models/hierarchical_model.py
vila/pdftools/__init__.py
vila/pdftools/base.py
vila/pdftools/datamodel.py
vila/pdftools/pdf_extractor.py
vila/pdftools/pdfplumber_extractor.py
vila-0.5.0.dist-info/LICENSE
vila-0.5.0.dist-info/METADATA
vila-0.5.0.dist-info/WHEEL
vila-0.5.0.dist-info/top_level.txt
vila-0.5.0.dist-info/RECORD
