Metadata-Version: 2.1
Name: vila
Version: 0.5.0
Home-page: https://github.com/allenai/vila
Author: Zejiang Shen
License: Apache-2.0
Requires-Python: >=3.6
License-File: LICENSE
Requires-Dist: torch (>=1.5)
Requires-Dist: torchvision (>=0.6.0)
Requires-Dist: pandas
Requires-Dist: pytest
Requires-Dist: pysbd
Requires-Dist: layoutparser[effdet] (>=0.2)
Requires-Dist: transformers
Requires-Dist: datasets
Requires-Dist: pdfplumber
Requires-Dist: pdf2image
Requires-Dist: tqdm
Requires-Dist: scikit-learn
